<?xml version="1.0" encoding="UTF-8"?>
<!-- Generated with glade 3.22.1 -->
<interface>
  <requires lib="gtk+" version="3.0"/>
  <object class="GtkImage" id="rabbitvcs-cancel">
    <property name="visible">True</property>
    <property name="can_focus">False</property>
    <property name="icon_name">rabbitvcs-cancel</property>
  </object>
  <object class="GtkImage" id="rabbitvcs-ok">
    <property name="visible">True</property>
    <property name="can_focus">False</property>
    <property name="icon_name">rabbitvcs-ok</property>
  </object>
  <object class="GtkDialog" id="TextChange">
    <property name="width_request">350</property>
    <property name="height_request">200</property>
    <property name="can_focus">False</property>
    <property name="events">GDK_POINTER_MOTION_MASK | GDK_POINTER_MOTION_HINT_MASK | GDK_BUTTON_PRESS_MASK | GDK_BUTTON_RELEASE_MASK</property>
    <property name="border_width">5</property>
    <property name="window_position">center-on-parent</property>
    <property name="icon_name">rabbitvcs-small</property>
    <property name="type_hint">dialog</property>
    <child>
      <placeholder/>
    </child>
    <child internal-child="vbox">
      <object class="GtkBox" id="dialog-vbox12">
        <property name="visible">True</property>
        <property name="can_focus">False</property>
        <property name="events">GDK_POINTER_MOTION_MASK | GDK_POINTER_MOTION_HINT_MASK | GDK_BUTTON_PRESS_MASK | GDK_BUTTON_RELEASE_MASK</property>
        <property name="hexpand">True</property>
        <property name="vexpand">True</property>
        <property name="orientation">vertical</property>
        <property name="spacing">18</property>
        <child internal-child="action_area">
          <object class="GtkButtonBox" id="dialog-action_area12">
            <property name="visible">True</property>
            <property name="can_focus">False</property>
            <property name="events">GDK_POINTER_MOTION_MASK | GDK_POINTER_MOTION_HINT_MASK | GDK_BUTTON_PRESS_MASK | GDK_BUTTON_RELEASE_MASK</property>
            <property name="halign">end</property>
            <property name="hexpand">True</property>
            <property name="layout_style">end</property>
            <child>
              <object class="GtkButton" id="textchange_cancel">
                <property name="label" translatable="yes">_Cancel</property>
                <property name="visible">True</property>
                <property name="can_focus">True</property>
                <property name="receives_default">True</property>
                <property name="events">GDK_POINTER_MOTION_MASK | GDK_POINTER_MOTION_HINT_MASK | GDK_BUTTON_PRESS_MASK | GDK_BUTTON_RELEASE_MASK</property>
                <property name="image">rabbitvcs-cancel</property>
                <property name="use_underline">True</property>
              </object>
              <packing>
                <property name="expand">False</property>
                <property name="fill">False</property>
                <property name="position">0</property>
              </packing>
            </child>
            <child>
              <object class="GtkButton" id="textchange_ok">
                <property name="label" translatable="yes">_OK</property>
                <property name="visible">True</property>
                <property name="can_focus">True</property>
                <property name="has_focus">True</property>
                <property name="can_default">True</property>
                <property name="has_default">True</property>
                <property name="receives_default">True</property>
                <property name="events">GDK_POINTER_MOTION_MASK | GDK_POINTER_MOTION_HINT_MASK | GDK_BUTTON_PRESS_MASK | GDK_BUTTON_RELEASE_MASK</property>
                <property name="image">rabbitvcs-ok</property>
                <property name="use_underline">True</property>
              </object>
              <packing>
                <property name="expand">False</property>
                <property name="fill">False</property>
                <property name="position">1</property>
              </packing>
            </child>
          </object>
          <packing>
            <property name="expand">False</property>
            <property name="fill">False</property>
            <property name="pack_type">end</property>
            <property name="position">0</property>
          </packing>
        </child>
        <child>
          <object class="GtkScrolledWindow" id="textchange_scrollwin">
            <property name="visible">True</property>
            <property name="can_focus">True</property>
            <property name="events">GDK_POINTER_MOTION_MASK | GDK_POINTER_MOTION_HINT_MASK | GDK_BUTTON_PRESS_MASK | GDK_BUTTON_RELEASE_MASK</property>
            <property name="margin_left">12</property>
            <property name="margin_right">12</property>
            <property name="margin_top">6</property>
            <property name="hexpand">True</property>
            <property name="vexpand">True</property>
            <property name="shadow_type">etched-in</property>
            <child>
              <object class="GtkTextView" id="textchange_message">
                <property name="visible">True</property>
                <property name="can_focus">True</property>
                <property name="events">GDK_POINTER_MOTION_MASK | GDK_POINTER_MOTION_HINT_MASK | GDK_BUTTON_PRESS_MASK | GDK_BUTTON_RELEASE_MASK</property>
                <property name="hexpand">True</property>
                <property name="vexpand">True</property>
                <property name="wrap_mode">word</property>
              </object>
            </child>
          </object>
          <packing>
            <property name="expand">True</property>
            <property name="fill">True</property>
            <property name="position">1</property>
          </packing>
        </child>
      </object>
    </child>
    <action-widgets>
      <action-widget response="-6">textchange_cancel</action-widget>
      <action-widget response="-5">textchange_ok</action-widget>
    </action-widgets>
  </object>
</interface>
